LICENSE
README.rst
dj_queryset_manager.py
setup.py
dj_queryset_manager.egg-info/PKG-INFO
dj_queryset_manager.egg-info/SOURCES.txt
dj_queryset_manager.egg-info/dependency_links.txt
dj_queryset_manager.egg-info/top_level.txt