Metadata-Version: 1.0
Name: dj-queryset-manager
Version: 0.1.1
Summary: Stop writing Django querysets.
Home-page: https://github.com/nosamanuel/dj-queryset-manager
Author: Noah Seger
Author-email: nosamanuel@gmail.com.com
License: Copyright (c) 2013, Noah Seger
